<?xml version="1.0" encoding="utf-8" ?>
<dwsync>
<file name="bg.gif" server="ftp.camarimbrincart.com.br" local="129044419200000000" remote="129044419200000000" />
<file name="left.gif" server="ftp.camarimbrincart.com.br" local="129044419200000000" remote="129044419200000000" />
<file name="left_first.gif" server="ftp.camarimbrincart.com.br" local="129044419200000000" remote="129044419200000000" />
<file name="left_on.gif" server="ftp.camarimbrincart.com.br" local="129044419200000000" remote="129044419200000000" />
<file name="left_over.gif" server="ftp.camarimbrincart.com.br" local="129044419200000000" remote="129044419200000000" />
<file name="right.gif" server="ftp.camarimbrincart.com.br" local="129044419200000000" remote="129044419200000000" />
<file name="right_last.gif" server="ftp.camarimbrincart.com.br" local="129044419200000000" remote="129044419200000000" />
<file name="right_on.gif" server="ftp.camarimbrincart.com.br" local="129044419200000000" remote="129044419200000000" />
</dwsync>